saigen_dep_test_with_poetry/__init__.py
saigen_dep_test_with_poetry/script.py
saigen_dep_test_with_poetry-0.1.0.dist-info/WHEEL
saigen_dep_test_with_poetry-0.1.0.dist-info/METADATA
saigen_dep_test_with_poetry-0.1.0.dist-info/RECORD
