Metadata-Version: 2.1
Name: saigen-dep-test-with-poetry
Version: 0.1.0
Summary: 
Author: francois_saigen
Author-email: francois@saigen.co.za
Requires-Python: >=3.8,<4.0
Classifier: Programming Language :: Python :: 3
Classifier: Programming Language :: Python :: 3.10
Classifier: Programming Language :: Python :: 3.8
Classifier: Programming Language :: Python :: 3.9
Requires-Dist: SoundFile (>=0.10.3,<0.11.0)
Requires-Dist: boto3 (>=1.24.40,<2.0.0)
Requires-Dist: librosa (>=0.9.2,<0.10.0)
Requires-Dist: requests (>=2.28.1,<3.0.0)
